{
  "name": "PVP 极限隐刀",
  "matchup": "PvP",
  "race": "Protoss",
  "leadTimeSec": 4,
  "steps": [
    { "time": 0,   "say": "探机" },
    { "time": 12,  "say": "探机" },
    { "time": 17,  "say": "水晶" },
    { "time": 24,  "say": "探机" },
    { "time": 35,  "say": "探机.星空加速" },
    { "time": 37,  "say": "传送门" },
    { "time": 47,  "say": "探机" },
    { "time": 48,  "say": "气矿 x2" },
    { "time": 55,  "say": "探机" },
    { "time": 64,  "say": "探机" },
    { "time": 68,  "say": "传送门" },
    { "time": 75,  "say": "探机" },
    { "time": 84,  "say": "控制芯核" },
    { "time": 87,  "say": "探机" },
    { "time": 99,  "say": "水晶" },
    { "time": 100, "say": "使徒 x2.星空加速" },
    { "time": 102, "say": "光影议会" },
    { "time": 105, "say": "升级折跃" },
    { "time": 132, "say": "水晶" },
    { "time": 141, "say": "追猎者" },
    { "time": 158, "say": "黑暗圣坛" },
    { "time": 161, "say": "追猎者" },
    { "time": 184, "say": "护盾充能器" },
    { "time": 195, "say": "探机" },
    { "time": 199, "say": "传送门" },
    { "time": 207, "say": "水晶.探机" },
    { "time": 233, "say": "隐刀 x2" }
  ]
}
