{
  "name": "ZVZ 三开狗毒爆压制",
  "matchup": "ZvZ",
  "race": "Zerg",
  "leadTimeSec": 4,
  "steps": [
    { "time": 0,   "say": "工蜂" },
    { "time": 12,  "say": "王虫" },
    { "time": 16,  "say": "工蜂" },
    { "time": 30,  "say": "工蜂 x2" },
    { "time": 48,  "say": "孵化场" },
    { "time": 51,  "say": "工蜂" },
    { "time": 55,  "say": "工蜂" },
    { "time": 59,  "say": "工蜂" },
    { "time": 70,  "say": "气矿" },
    { "time": 75,  "say": "血池" },
    { "time": 79,  "say": "工蜂 x2" },
    { "time": 89,  "say": "工蜂" },
    { "time": 100, "say": "工蜂" },
    { "time": 110, "say": "王虫" },
    { "time": 122, "say": "女王 x2.小狗 x4" },
    { "time": 134, "say": "工蜂 x2" },
    { "time": 137, "say": "狗速" },
    { "time": 146, "say": "工蜂 x2" },
    { "time": 155, "say": "孵化场.工蜂" },
    { "time": 158, "say": "注卵 x2.工蜂 x2" },
    { "time": 173, "say": "毒爆虫巢" },
    { "time": 189, "say": "工蜂.王虫" },
    { "time": 192, "say": "工蜂.女王" },
    { "time": 204, "say": "注卵 x2.小狗" },
    { "time": 212, "say": "进攻.毒爆" },
    { "time": 220, "say": "注卵 x2.小狗" }
  ]
}
